cloudtools/__init__.py
cloudtools/__main__.py
cloudtools/cluster_config.py
cloudtools/connect.py
cloudtools/describe.py
cloudtools/diagnose.py
cloudtools/init_notebook.py
cloudtools/latest.py
cloudtools/list_clusters.py
cloudtools/modify.py
cloudtools/safe_call.py
cloudtools/start.py
cloudtools/stop.py
cloudtools/submit.py
cloudtools/utils.py
cloudtools-4.3.0.dist-info/METADATA
cloudtools-4.3.0.dist-info/RECORD
cloudtools-4.3.0.dist-info/WHEEL
cloudtools-4.3.0.dist-info/entry_points.txt
cloudtools-4.3.0.dist-info/top_level.txt
