Metadata-Version: 2.1
Name: cloudtools
Version: 4.3.0
Summary: Collection of utilities for working on the Google Cloud Platform.
Home-page: https://github.com/Nealelab/cloudtools
Author: Liam Abbott
Author-email: labbott@broadinstitute.org
License: MIT
Keywords: google cloud dataproc spark jupyter hail notebook ipython
Platform: UNKNOWN
Classifier: Development Status :: 3 - Alpha
Classifier: License :: OSI Approved :: MIT License
Classifier: Programming Language :: Python :: 3.6
Requires-Dist: statistics; python_version < "3.4"
